jhjag/__init__.py
jhjag/fetch_corrections.py
jhjag/submit_button.py
jhjag-1.0.dist-info/METADATA
jhjag-1.0.dist-info/WHEEL
jhjag-1.0.dist-info/licenses/LICENSE
jhjag-1.0.dist-info/RECORD
